[
    {
        "name": "Aammiq",
        "wikipediaURL": "https://en.wikipedia.org/wiki/Aammiq",
        "location": {
            "latitude": 33.731431,
            "longitude": 35.788983
        },
        "inhabitation": {
            "start": -12000
        }
    },
    {
        "name": "Jabal es Saaïdé",
        "wikipediaURL": "https://en.wikipedia.org/wiki/Jabal_es_Saa%C3%AFd%C3%A9",
        "location": {
            "latitude": 34.155444,
            "longitude": 36.228847
        },
        "inhabitation": {
            "start": -9999
        }
    },
    {
        "name": "Tell es-Sultan",
        "wikipediaURL": "https://en.wikipedia.org/wiki/Tell_es-Sultan",
        "location": {
            "latitude": 31.87171944,
            "longitude": 35.44456389
        },
        "inhabitation": {
            "start": -9600
        }
    },
    {
        "name": "Jericho",
        "wikipediaURL": "https://en.wikipedia.org/wiki/Jericho",
        "location": {
            "latitude": 31.856111111,
            "longitude": 35.463055555
        },
        "inhabitation": {
            "start": -9600
        }
    },
    {
        "name": "Star Carr",
        "wikipediaURL": "https://en.wikipedia.org/wiki/Star_Carr",
        "location": {
            "latitude": 54.2143,
            "longitude": -0.423661
        },
        "inhabitation": {
            "start": -8770
        }
    },
    {
        "name": "Aşıklı Höyük",
        "wikipediaURL": "https://en.wikipedia.org/wiki/A%C5%9F%C4%B1kl%C4%B1_H%C3%B6y%C3%BCk",
        "location": {
            "latitude": 38.349,
            "longitude": 34.23
        },
        "inhabitation": {
            "start": -8200
        }
    },
    {
        "name": "Byblos",
        "wikipediaURL": "https://en.wikipedia.org/wiki/Byblos",
        "location": {
            "latitude": 34.116666666,
            "longitude": 35.65
        },
        "inhabitation": {
            "start": -8000
        }
    },
    {
        "name": "Çatalhöyük",
        "wikipediaURL": "https://en.wikipedia.org/wiki/%C3%87atalh%C3%B6y%C3%BCk",
        "location": {
            "latitude": 37.6675,
            "longitude": 32.828333333
        },
        "inhabitation": {
            "start": -7499
        }
    },
    {
        "name": "Ba'ja",
        "wikipediaURL": "https://en.wikipedia.org/wiki/Ba%27ja",
        "location": {
            "latitude": 30.41361111,
            "longitude": 35.46138889
        },
        "inhabitation": {
            "start": -7400
        }
    },
    {
        "name": "Bouqras",
        "wikipediaURL": "https://en.wikipedia.org/wiki/Bouqras",
        "location": {
            "latitude": 35.016667,
            "longitude": 40.383333
        },
        "inhabitation": {
            "start": -7400
        }
    },
    {
        "name": "Chogha Bonut",
        "wikipediaURL": "https://en.wikipedia.org/wiki/Chogha_Bonut",
        "location": {
            "latitude": 32.222222,
            "longitude": 48.505
        },
        "inhabitation": {
            "start": -7200
        }
    },
    {
        "name": "Hacılar Mound",
        "wikipediaURL": "https://en.wikipedia.org/wiki/Hacilar",
        "location": {
            "latitude": 37.5843,
            "longitude": 30.0845
        },
        "inhabitation": {
            "start": -7040
        }
    },
    {
        "name": "Athens",
        "wikipediaURL": "https://en.wikipedia.org/wiki/Athens",
        "location": {
            "latitude": 37.984166666,
            "longitude": 23.728055555
        },
        "inhabitation": {
            "start": -7000
        }
    },
    {
        "name": "Knossos",
        "wikipediaURL": "https://en.wikipedia.org/wiki/Knossos",
        "location": {
            "latitude": 35.297961111,
            "longitude": 25.163155555
        },
        "inhabitation": {
            "start": -6999
        }
    },
    {
        "name": "Atlit Yam",
        "wikipediaURL": "https://en.wikipedia.org/wiki/Atlit_Yam",
        "location": {
            "latitude": 32.710827777,
            "longitude": 34.93515
        },
        "inhabitation": {
            "start": -6899
        }
    },
    {
        "name": "Ugarit",
        "wikipediaURL": "https://en.wikipedia.org/wiki/Ugarit",
        "location": {
            "latitude": 35.601944,
            "longitude": 35.785556
        },
        "inhabitation": {
            "start": -6000
        }
    },
    {
        "name": "Adana",
        "wikipediaURL": "https://en.wikipedia.org/wiki/Adana",
        "location": {
            "latitude": 37.00262,
            "longitude": 35.31346
        },
        "inhabitation": {
            "start": -6000
        }
    },
    {
        "name": "Singidunum",
        "wikipediaURL": "https://en.wikipedia.org/wiki/Singidunum",
        "location": {
            "latitude": 44.82,
            "longitude": 20.46
        },
        "inhabitation": {
            "start": -6000
        }
    },
    {
        "name": "Amsa-dong",
        "wikipediaURL": "https://en.wikipedia.org/wiki/Amsa-dong",
        "location": {
            "latitude": 37.560494,
            "longitude": 127.130214
        },
        "inhabitation": {
            "start": -5000
        }
    },
    {
        "name": "Aleppo",
        "wikipediaURL": "https://en.wikipedia.org/wiki/Aleppo",
        "location": {
            "latitude": 36.2,
            "longitude": 37.16
        },
        "inhabitation": {
            "start": -5000
        }
    },
    {
        "name": "Fatehpora",
        "wikipediaURL": "https://en.wikipedia.org/wiki/Fatehpora",
        "location": {
            "latitude": 33.653888888,
            "longitude": 75.156111111
        },
        "inhabitation": {
            "start": -5000
        }
    },
    {
        "name": "Anantnag",
        "wikipediaURL": "https://en.wikipedia.org/wiki/Anantnag",
        "location": {
            "latitude": 33.73,
            "longitude": 75.15
        },
        "inhabitation": {
            "start": -5000
        }
    },
    {
        "name": "Goseck circle",
        "wikipediaURL": "https://en.wikipedia.org/wiki/Goseck_Circle",
        "location": {
            "latitude": 51.198333333,
            "longitude": 11.864722222
        },
        "inhabitation": {
            "start": -4900
        }
    },
    {
        "name": "Merimde culture",
        "wikipediaURL": "https://en.wikipedia.org/wiki/Merimde_culture",
        "location": {
            "latitude": 30.320833333,
            "longitude": 30.848888888
        },
        "inhabitation": {
            "start": -4800
        }
    },
    {
        "name": "Solnitsata",
        "wikipediaURL": "https://en.wikipedia.org/wiki/Solnitsata",
        "location": {
            "latitude": 43.128417,
            "longitude": 27.472528
        },
        "inhabitation": {
            "start": -4700
        }
    },
    {
        "name": "Milakpur",
        "wikipediaURL": "https://en.wikipedia.org/wiki/Milakpur",
        "location": {
            "latitude": 27.55,
            "longitude": 76.86666667
        },
        "inhabitation": {
            "start": -4700
        }
    },
    {
        "name": "Sisai, Hisar",
        "wikipediaURL": "https://en.wikipedia.org/wiki/Sisai,_Hisar",
        "location": {
            "latitude": 29.179,
            "longitude": 76.008
        },
        "inhabitation": {
            "start": -4700
        }
    },
    {
        "name": "Mangesh",
        "wikipediaURL": "https://en.wikipedia.org/wiki/Mangesh,_Iraq",
        "location": {
            "latitude": 37.03333333,
            "longitude": 43.1
        },
        "inhabitation": {
            "start": -4500
        }
    },
    {
        "name": "Susa",
        "wikipediaURL": "https://en.wikipedia.org/wiki/Susa",
        "location": {
            "latitude": 32.189444444,
            "longitude": 48.256111111
        },
        "inhabitation": {
            "start": -4394
        }
    },
    {
        "name": "Aqaba",
        "wikipediaURL": "https://en.wikipedia.org/wiki/Aqaba",
        "location": {
            "latitude": 29.532222222,
            "longitude": 35.006111111
        },
        "inhabitation": {
            "start": -4000
        }
    },
    {
        "name": "Der",
        "wikipediaURL": "https://en.wikipedia.org/wiki/Der_(Sumer)",
        "location": {
            "latitude": 33.123611111,
            "longitude": 45.931388888
        },
        "inhabitation": {
            "start": -4000
        }
    },
    {
        "name": "Jerusalem",
        "wikipediaURL": "https://en.wikipedia.org/wiki/Jerusalem",
        "location": {
            "latitude": 31.778888888,
            "longitude": 35.225555555
        },
        "inhabitation": {
            "start": -4000
        }
    },
    {
        "name": "Anshan Persia",
        "wikipediaURL": "https://en.wikipedia.org/wiki/Anshan_(Persia)",
        "location": {
            "latitude": 30.011666666,
            "longitude": 52.407777777
        },
        "inhabitation": {
            "start": -3999
        }
    },
    {
        "name": "Susa",
        "wikipediaURL": "https://en.wikipedia.org/wiki/Susa",
        "location": {
            "latitude": 32.189444444,
            "longitude": 48.256111111
        },
        "inhabitation": {
            "start": -3999
        }
    },
    {
        "name": "Thinis",
        "wikipediaURL": "https://en.wikipedia.org/wiki/Thinis",
        "location": {
            "latitude": 26.333333333,
            "longitude": 31.9
        },
        "inhabitation": {
            "start": -3999
        }
    },
    {
        "name": "Chiplun",
        "wikipediaURL": "https://en.wikipedia.org/wiki/Chiplun",
        "location": {
            "latitude": 17.53,
            "longitude": 73.52
        },
        "inhabitation": {
            "start": -3999
        }
    },
    {
        "name": "Beit She'an",
        "wikipediaURL": "https://en.wikipedia.org/wiki/Beit_She%27an",
        "location": {
            "latitude": 32.496111111,
            "longitude": 35.498888888
        },
        "inhabitation": {
            "start": -3999
        }
    },
    {
        "name": "Ur",
        "wikipediaURL": "https://en.wikipedia.org/wiki/Ur",
        "location": {
            "latitude": 30.962222,
            "longitude": 46.104444
        },
        "inhabitation": {
            "start": -3799
        }
    },
    {
        "name": "Salamiyah",
        "wikipediaURL": "https://en.wikipedia.org/wiki/Salamiyah",
        "location": {
            "latitude": 35.011111111,
            "longitude": 37.053055555
        },
        "inhabitation": {
            "start": -3499
        }
    },
    {
        "name": "Vashisht, Himachal Pradesh",
        "wikipediaURL": "https://en.wikipedia.org/wiki/Vashisht,_Himachal_Pradesh",
        "location": {
            "latitude": 32.25888889,
            "longitude": 77.19
        },
        "inhabitation": {
            "start": -3499
        }
    },
    {
        "name": "Dundalk",
        "wikipediaURL": "https://en.wikipedia.org/wiki/Dundalk",
        "location": {
            "latitude": 54.004444444,
            "longitude": -6.400277777
        },
        "inhabitation": {
            "start": -3499
        }
    },
    {
        "name": "Horgen",
        "wikipediaURL": "https://en.wikipedia.org/wiki/Horgen",
        "location": {
            "latitude": 47.260833333,
            "longitude": 8.5975
        },
        "inhabitation": {
            "start": -3399
        }
    },
    {
        "name": "Abu Salabikh",
        "wikipediaURL": "https://en.wikipedia.org/wiki/Abu_Salabikh",
        "location": {
            "latitude": 32.266667,
            "longitude": 45.083333
        },
        "inhabitation": {
            "start": -3399
        }
    },
    {
        "name": "Uruk",
        "wikipediaURL": "https://en.wikipedia.org/wiki/Uruk",
        "location": {
            "latitude": 31.3259,
            "longitude": 45.6374
        },
        "inhabitation": {
            "start": -3199
        }
    },
    {
        "name": "Thebes",
        "wikipediaURL": "https://en.wikipedia.org/wiki/Thebes,_Egypt",
        "location": {
            "latitude": 25.720555555,
            "longitude": 32.610277777
        },
        "inhabitation": {
            "start": -3199
        }
    },
    {
        "name": "Skara Brae",
        "wikipediaURL": "https://en.wikipedia.org/wiki/Skara_Brae",
        "location": {
            "latitude": 59.0487138,
            "longitude": -3.3417499
        },
        "inhabitation": {
            "start": -3179
        }
    },
    {
        "name": "Kish",
        "wikipediaURL": "https://en.wikipedia.org/wiki/Kish_(Sumer)",
        "location": {
            "latitude": 32.540277777,
            "longitude": 44.604722222
        },
        "inhabitation": {
            "start": -3099
        }
    },
    {
        "name": "Asyut",
        "wikipediaURL": "https://en.wikipedia.org/wiki/Asyut",
        "location": {
            "latitude": 27.186944444,
            "longitude": 31.171388888
        },
        "inhabitation": {
            "start": -3099
        }
    },
    {
        "name": "Phaistos",
        "wikipediaURL": "https://en.wikipedia.org/wiki/Phaistos",
        "location": {
            "latitude": 35.05123,
            "longitude": 24.814267
        },
        "inhabitation": {
            "start": -3000
        }
    },
    {
        "name": "İzmir",
        "wikipediaURL": "https://en.wikipedia.org/wiki/%C4%B0zmir",
        "location": {
            "latitude": 38.41273,
            "longitude": 27.13838
        },
        "inhabitation": {
            "start": -3000
        }
    },
    {
        "name": "Amedi",
        "wikipediaURL": "https://en.wikipedia.org/wiki/Amedi",
        "location": {
            "latitude": 37.0919,
            "longitude": 43.487
        },
        "inhabitation": {
            "start": -3000
        }
    },
    {
        "name": "Troy",
        "wikipediaURL": "https://en.wikipedia.org/wiki/Troy",
        "location": {
            "latitude": 39.9575,
            "longitude": 26.238888888
        },
        "inhabitation": {
            "start": -2999
        }
    },
    {
        "name": "Tulkarm",
        "wikipediaURL": "https://en.wikipedia.org/wiki/Tulkarm",
        "location": {
            "latitude": 32.311111111,
            "longitude": 35.030833333
        },
        "inhabitation": {
            "start": -2999
        }
    },
    {
        "name": "Kozan",
        "wikipediaURL": "https://en.wikipedia.org/wiki/Kozan,_Adana",
        "location": {
            "latitude": 37.4507,
            "longitude": 35.812347222
        },
        "inhabitation": {
            "start": -2999
        }
    },
    {
        "name": "Zincirli Höyük",
        "wikipediaURL": "https://en.wikipedia.org/wiki/Sam%CA%BEal",
        "location": {
            "latitude": 37.103611111,
            "longitude": 36.678611111
        },
        "inhabitation": {
            "start": -2999
        }
    },
    {
        "name": "Ebla",
        "wikipediaURL": "https://en.wikipedia.org/wiki/Ebla",
        "location": {
            "latitude": 35.798056,
            "longitude": 36.798611
        },
        "inhabitation": {
            "start": -2999
        }
    },
    {
        "name": "Royal Cemetery at Ur",
        "wikipediaURL": "https://en.wikipedia.org/wiki/Royal_Cemetery_at_Ur",
        "location": {
            "latitude": 30.962,
            "longitude": 46.1047
        },
        "inhabitation": {
            "start": -2999
        }
    },
    {
        "name": "Badrashin",
        "wikipediaURL": "https://en.wikipedia.org/wiki/Badrashin",
        "location": {
            "latitude": 29.851388888,
            "longitude": 31.274166666
        },
        "inhabitation": {
            "start": -2999
        }
    },
    {
        "name": "Jiskairumoko",
        "wikipediaURL": "https://en.wikipedia.org/wiki/Jisk%27a_Iru_Muqu",
        "location": {
            "latitude": -16.21111111,
            "longitude": -69.76388889
        },
        "inhabitation": {
            "start": -2999
        }
    },
    {
        "name": "Mari",
        "wikipediaURL": "https://en.wikipedia.org/wiki/Mari,_Syria",
        "location": {
            "latitude": 34.549444444,
            "longitude": 40.89
        },
        "inhabitation": {
            "start": -2900
        }
    },
    {
        "name": "Bamyan",
        "wikipediaURL": "https://en.wikipedia.org/wiki/Bamyan",
        "location": {
            "latitude": 34.816666666,
            "longitude": 67.816666666
        },
        "inhabitation": {
            "start": -2799
        }
    },
    {
        "name": "Tyre",
        "wikipediaURL": "https://en.wikipedia.org/wiki/Tyre,_Lebanon",
        "location": {
            "latitude": 33.266666666,
            "longitude": 35.2
        },
        "inhabitation": {
            "start": -2749
        }
    },
    {
        "name": "Dahshur",
        "wikipediaURL": "https://en.wikipedia.org/wiki/Dahshur",
        "location": {
            "latitude": 29.8,
            "longitude": 31.233333333
        },
        "inhabitation": {
            "start": -2588
        }
    },
    {
        "name": "Phong Châu",
        "wikipediaURL": "https://en.wikipedia.org/wiki/Phong_Ch%C3%A2u",
        "location": {
            "latitude": 21.2817,
            "longitude": 105.442
        },
        "inhabitation": {
            "start": -2523
        }
    },
    {
        "name": "Lagash",
        "wikipediaURL": "https://en.wikipedia.org/wiki/Lagash",
        "location": {
            "latitude": 31.411389,
            "longitude": 46.407222
        },
        "inhabitation": {
            "start": -2500
        }
    },
    {
        "name": "Meroë",
        "wikipediaURL": "https://en.wikipedia.org/wiki/Mero%C3%AB",
        "location": {
            "latitude": 16.935138888,
            "longitude": 33.75075
        },
        "inhabitation": {
            "start": -2500
        }
    },
    {
        "name": "Assur",
        "wikipediaURL": "https://en.wikipedia.org/wiki/Assur",
        "location": {
            "latitude": 35.456666666,
            "longitude": 43.2625
        },
        "inhabitation": {
            "start": -2499
        }
    },
    {
        "name": "Abarsal",
        "wikipediaURL": "https://en.wikipedia.org/wiki/Abarsal",
        "location": {
            "latitude": 36.113054,
            "longitude": 38.000883
        },
        "inhabitation": {
            "start": -2419
        }
    },
    {
        "name": "Lothal",
        "wikipediaURL": "https://en.wikipedia.org/wiki/Lothal",
        "location": {
            "latitude": 22.521388888,
            "longitude": 72.249444444
        },
        "inhabitation": {
            "start": -2399
        }
    },
    {
        "name": "Babylon",
        "wikipediaURL": "https://en.wikipedia.org/wiki/Babylon",
        "location": {
            "latitude": 32.5425,
            "longitude": 44.421111111
        },
        "inhabitation": {
            "start": -2200
        }
    },
    {
        "name": "Nazareth",
        "wikipediaURL": "https://en.wikipedia.org/wiki/Nazareth",
        "location": {
            "latitude": 32.702102777,
            "longitude": 35.29785
        },
        "inhabitation": {
            "start": -2199
        }
    },
    {
        "name": "Sicyon",
        "wikipediaURL": "https://en.wikipedia.org/wiki/Sicyon",
        "location": {
            "latitude": 37.984104,
            "longitude": 22.711145
        },
        "inhabitation": {
            "start": -2000
        }
    },
    {
        "name": "Uplistsikhe",
        "wikipediaURL": "https://en.wikipedia.org/wiki/Uplistsikhe",
        "location": {
            "latitude": 41.966664,
            "longitude": 44.207505
        },
        "inhabitation": {
            "start": -2000
        }
    },
    {
        "name": "Tell Ubeidiya",
        "wikipediaURL": "https://en.wikipedia.org/wiki/Ubeidiya,_Tiberias",
        "location": {
            "latitude": 32.688888888,
            "longitude": 35.561666666
        },
        "inhabitation": {
            "start": -2000
        }
    },
    {
        "name": "Thebes",
        "wikipediaURL": "https://en.wikipedia.org/wiki/Thebes,_Greece",
        "location": {
            "latitude": 38.320833333,
            "longitude": 23.317777777
        },
        "inhabitation": {
            "start": -2000
        }
    },
    {
        "name": "Najran",
        "wikipediaURL": "https://en.wikipedia.org/wiki/Najran",
        "location": {
            "latitude": 17.4917,
            "longitude": 44.1322
        },
        "inhabitation": {
            "start": -1999
        }
    },
    {
        "name": "Homs",
        "wikipediaURL": "https://en.wikipedia.org/wiki/Homs",
        "location": {
            "latitude": 34.733333333,
            "longitude": 36.716666666
        },
        "inhabitation": {
            "start": -1999
        }
    },
    {
        "name": "Bareq",
        "wikipediaURL": "https://en.wikipedia.org/wiki/Bareq",
        "location": {
            "latitude": 18.9322222,
            "longitude": 41.9438889
        },
        "inhabitation": {
            "start": -1999
        }
    },
    {
        "name": "Sabadell",
        "wikipediaURL": "https://en.wikipedia.org/wiki/Sabadell",
        "location": {
            "latitude": 41.548333333,
            "longitude": 2.1075
        },
        "inhabitation": {
            "start": -1799
        }
    },
    {
        "name": "Rhodes",
        "wikipediaURL": "https://en.wikipedia.org/wiki/Rhodes",
        "location": {
            "latitude": 36.17,
            "longitude": 27.92
        },
        "inhabitation": {
            "start": -1600
        }
    },
    {
        "name": "Gaza City",
        "wikipediaURL": "https://en.wikipedia.org/wiki/Gaza_City",
        "location": {
            "latitude": 31.5075,
            "longitude": 34.459722222
        },
        "inhabitation": {
            "start": -1500
        }
    },
    {
        "name": "Thermos",
        "wikipediaURL": "https://en.wikipedia.org/wiki/Thermos_(Aetolia)",
        "location": {
            "latitude": 38.559853,
            "longitude": 21.668664
        },
        "inhabitation": {
            "start": -1499
        }
    },
    {
        "name": "Asilah",
        "wikipediaURL": "https://en.wikipedia.org/wiki/Asilah",
        "location": {
            "latitude": 35.466666666,
            "longitude": -6.033333333
        },
        "inhabitation": {
            "start": -1499
        }
    },
    {
        "name": "Nakhchivan",
        "wikipediaURL": "https://en.wikipedia.org/wiki/Nakhchivan_(city)",
        "location": {
            "latitude": 39.208888888,
            "longitude": 45.412222222
        },
        "inhabitation": {
            "start": -1499
        }
    },
    {
        "name": "Acre",
        "wikipediaURL": "https://en.wikipedia.org/wiki/Acre,_Israel",
        "location": {
            "latitude": 32.926111111,
            "longitude": 35.083888888
        },
        "inhabitation": {
            "start": -1499
        }
    },
    {
        "name": "Adulis",
        "wikipediaURL": "https://en.wikipedia.org/wiki/Adulis",
        "location": {
            "latitude": 15.263611111,
            "longitude": 39.660555555
        },
        "inhabitation": {
            "start": -1449
        }
    },
    {
        "name": "Irbid",
        "wikipediaURL": "https://en.wikipedia.org/wiki/Irbid",
        "location": {
            "latitude": 32.555555555,
            "longitude": 35.85
        },
        "inhabitation": {
            "start": -1399
        }
    },
    {
        "name": "Amarna",
        "wikipediaURL": "https://en.wikipedia.org/wiki/Amarna",
        "location": {
            "latitude": 27.661666666,
            "longitude": 30.905555555
        },
        "inhabitation": {
            "start": -1352
        }
    },
    {
        "name": "Tarḫuntašša",
        "wikipediaURL": "https://en.wikipedia.org/wiki/Tar%E1%B8%ABunta%C5%A1%C5%A1a",
        "location": {
            "latitude": 36.86666667,
            "longitude": 33.16666667
        },
        "inhabitation": {
            "start": -1294
        }
    },
    {
        "name": "Pithom",
        "wikipediaURL": "https://en.wikipedia.org/wiki/Pithom",
        "location": {
            "latitude": 30.551944444,
            "longitude": 32.098611111
        },
        "inhabitation": {
            "start": -1277
        }
    },
    {
        "name": "Pi-Ramesses",
        "wikipediaURL": "https://en.wikipedia.org/wiki/Pi-Ramesses",
        "location": {
            "latitude": 30.79937,
            "longitude": 31.834217
        },
        "inhabitation": {
            "start": -1277
        }
    },
    {
        "name": "Alba Longa",
        "wikipediaURL": "https://en.wikipedia.org/wiki/Alba_Longa",
        "location": {
            "latitude": 41.74691,
            "longitude": 12.65026
        },
        "inhabitation": {
            "start": -1200
        }
    },
    {
        "name": "Idalion",
        "wikipediaURL": "https://en.wikipedia.org/wiki/Idalion",
        "location": {
            "latitude": 35.015833333,
            "longitude": 33.423055555
        },
        "inhabitation": {
            "start": -1200
        }
    },
    {
        "name": "Padua",
        "wikipediaURL": "https://en.wikipedia.org/wiki/Padua",
        "location": {
            "latitude": 45.407777777,
            "longitude": 11.873333333
        },
        "inhabitation": {
            "start": -1182
        }
    },
    {
        "name": "Soli",
        "wikipediaURL": "https://en.wikipedia.org/wiki/Soli,_Cyprus",
        "location": {
            "latitude": 35.1404,
            "longitude": 32.8126
        },
        "inhabitation": {
            "start": -1100
        }
    },
    {
        "name": "Colophon",
        "wikipediaURL": "https://en.wikipedia.org/wiki/Colophon_(city)",
        "location": {
            "latitude": 38.11555556,
            "longitude": 27.14222222
        },
        "inhabitation": {
            "start": -1100
        }
    },
    {
        "name": "Salamis",
        "wikipediaURL": "https://en.wikipedia.org/wiki/Salamis,_Cyprus",
        "location": {
            "latitude": 35.183333333,
            "longitude": 33.9
        },
        "inhabitation": {
            "start": -1100
        }
    },
    {
        "name": "Miletus",
        "wikipediaURL": "https://en.wikipedia.org/wiki/Miletus",
        "location": {
            "latitude": 37.531111,
            "longitude": 27.275556
        },
        "inhabitation": {
            "start": -1100
        }
    },
    {
        "name": "Endor",
        "wikipediaURL": "https://en.wikipedia.org/wiki/Endor_(village)",
        "location": {
            "latitude": 32.65619722,
            "longitude": 35.46709722
        },
        "inhabitation": {
            "start": -1100
        }
    },
    {
        "name": "Halicarnassus",
        "wikipediaURL": "https://en.wikipedia.org/wiki/Halicarnassus",
        "location": {
            "latitude": 37.037778,
            "longitude": 27.424167
        },
        "inhabitation": {
            "start": -1099
        }
    },
    {
        "name": "Elis",
        "wikipediaURL": "https://en.wikipedia.org/wiki/Elis_(city)",
        "location": {
            "latitude": 37.892222222,
            "longitude": 21.374444444
        },
        "inhabitation": {
            "start": -1099
        }
    },
    {
        "name": "Knidos",
        "wikipediaURL": "https://en.wikipedia.org/wiki/Knidos",
        "location": {
            "latitude": 36.685833,
            "longitude": 27.375
        },
        "inhabitation": {
            "start": -1099
        }
    },
    {
        "name": "Kourion",
        "wikipediaURL": "https://en.wikipedia.org/wiki/Kourion",
        "location": {
            "latitude": 34.6642,
            "longitude": 32.8877
        },
        "inhabitation": {
            "start": -1050
        }
    },
    {
        "name": "Fenghao",
        "wikipediaURL": "https://en.wikipedia.org/wiki/Fenghao",
        "location": {
            "latitude": 34.21,
            "longitude": 108.72
        },
        "inhabitation": {
            "start": -1050
        }
    },
    {
        "name": "Wangcheng",
        "wikipediaURL": "https://en.wikipedia.org/wiki/Wangcheng_(Zhou_dynasty)",
        "location": {
            "latitude": 34.66768,
            "longitude": 112.41452
        },
        "inhabitation": {
            "start": -1020
        }
    },
    {
        "name": "Lapathus",
        "wikipediaURL": "https://en.wikipedia.org/wiki/Lapathus_(Cyprus)",
        "location": {
            "latitude": 35.35583333,
            "longitude": 33.19555556
        },
        "inhabitation": {
            "start": -1000
        }
    },
    {
        "name": "Ephesus",
        "wikipediaURL": "https://en.wikipedia.org/wiki/Ephesus",
        "location": {
            "latitude": 37.939722,
            "longitude": 27.348611
        },
        "inhabitation": {
            "start": -1000
        }
    },
    {
        "name": "Eleutheropolis",
        "wikipediaURL": "https://en.wikipedia.org/wiki/Eleutheropolis",
        "location": {
            "latitude": 31.613097,
            "longitude": 34.898297
        },
        "inhabitation": {
            "start": -1000
        }
    },
    {
        "name": "Nokalakevi",
        "wikipediaURL": "https://en.wikipedia.org/wiki/Nokalakevi",
        "location": {
            "latitude": 42.35722222,
            "longitude": 42.19388889
        },
        "inhabitation": {
            "start": -1000
        }
    }
]